NCryptoClient/LICENSE
NCryptoClient/__init__.py
NCryptoClient/client_instance_holder.py
NCryptoClient/launcher.py
NCryptoClient/main_window.py
NCryptoClient/Config/autoexec — копия.ini
NCryptoClient/Config/autoexec.ini
NCryptoClient/Config/~autoexec1.ini
NCryptoClient/Img/NCryptoLogo_750x206.png
NCryptoClient/Img/add_24x24.png
NCryptoClient/Img/remove_24x24.png
NCryptoClient/Log/__init__.py
NCryptoClient/Log/client.log
NCryptoClient/Log/client_log_config.py
NCryptoClient/Log/__pycache__/__init__.cpython-36.pyc
NCryptoClient/Log/__pycache__/client_log_config.cpython-36.pyc
NCryptoClient/Transmitter/__init__.py
NCryptoClient/Transmitter/client_handler.py
NCryptoClient/Transmitter/client_receiver.py
NCryptoClient/Transmitter/client_sender.py
NCryptoClient/Transmitter/__pycache__/__init__.cpython-36.pyc
NCryptoClient/Transmitter/__pycache__/client_handler.cpython-36.pyc
NCryptoClient/Transmitter/__pycache__/client_receiver.cpython-36.pyc
NCryptoClient/Transmitter/__pycache__/client_sender.cpython-36.pyc
NCryptoClient/UI/__init__.py
NCryptoClient/UI/ui_chat_tab.py
NCryptoClient/UI/ui_contacts_list.py
NCryptoClient/UI/ui_main_window.py
NCryptoClient/UI/ui_server_settings_window.py
NCryptoClient/UI/Templates/MainWindow.ui
NCryptoClient/UI/Templates/ServerSettings.ui
NCryptoClient/UI/__pycache__/__init__.cpython-36.pyc
NCryptoClient/UI/__pycache__/ui_chat_tab.cpython-36.pyc
NCryptoClient/UI/__pycache__/ui_contacts_list.cpython-36.pyc
NCryptoClient/UI/__pycache__/ui_main_window.cpython-36.pyc
NCryptoClient/UI/__pycache__/ui_server_settings_window.cpython-36.pyc
NCryptoClient/Utils/__init__.py
NCryptoClient/Utils/client_file_manager.py
NCryptoClient/Utils/constants.py
NCryptoClient/Utils/__pycache__/__init__.cpython-36.pyc
NCryptoClient/Utils/__pycache__/client_file_manager.cpython-36.pyc
NCryptoClient/Utils/__pycache__/constants.cpython-36.pyc
NCryptoClient/__pycache__/__init__.cpython-36.pyc
NCryptoClient-0.5.1.dist-info/METADATA
NCryptoClient-0.5.1.dist-info/RECORD
NCryptoClient-0.5.1.dist-info/WHEEL
NCryptoClient-0.5.1.dist-info/entry_points.txt
NCryptoClient-0.5.1.dist-info/top_level.txt
